chainlit/__init__.py
chainlit/__main__.py
chainlit/_utils.py
chainlit/action.py
chainlit/auth/__init__.py
chainlit/auth/cookie.py
chainlit/auth/jwt.py
chainlit/cache.py
chainlit/callbacks.py
chainlit/chat_context.py
chainlit/chat_settings.py
chainlit/cli/__init__.py
chainlit/config.py
chainlit/context.py
chainlit/copilot/dist/assets/logo_dark-2a3cf740.svg
chainlit/copilot/dist/assets/logo_light-b078e7bc.svg
chainlit/copilot/dist/index.js
chainlit/data/__init__.py
chainlit/data/acl.py
chainlit/data/base.py
chainlit/data/chainlit_data_layer.py
chainlit/data/dynamodb.py
chainlit/data/literalai.py
chainlit/data/sql_alchemy.py
chainlit/data/storage_clients/__init__.py
chainlit/data/storage_clients/azure.py
chainlit/data/storage_clients/azure_blob.py
chainlit/data/storage_clients/base.py
chainlit/data/storage_clients/gcs.py
chainlit/data/storage_clients/s3.py
chainlit/data/utils.py
chainlit/discord/__init__.py
chainlit/discord/app.py
chainlit/element.py
chainlit/emitter.py
chainlit/frontend/dist/assets/DailyMotion-b4b7af47.js
chainlit/frontend/dist/assets/Facebook-572972a0.js
chainlit/frontend/dist/assets/FilePlayer-85c69ca8.js
chainlit/frontend/dist/assets/Kaltura-dfc24672.js
chainlit/frontend/dist/assets/Mixcloud-705011f4.js
chainlit/frontend/dist/assets/Mux-4201a9e6.js
chainlit/frontend/dist/assets/Preview-23ba40a6.js
chainlit/frontend/dist/assets/SoundCloud-1a582d51.js
chainlit/frontend/dist/assets/Streamable-5017c4ba.js
chainlit/frontend/dist/assets/Twitch-bb2de2fa.js
chainlit/frontend/dist/assets/Vidyard-54e269b1.js
chainlit/frontend/dist/assets/Vimeo-d92c37dd.js
chainlit/frontend/dist/assets/Wistia-25a1363b.js
chainlit/frontend/dist/assets/YouTube-616e8cb7.js
chainlit/frontend/dist/assets/index-aaf974a9.css
chainlit/frontend/dist/assets/index-f5df2072.js
chainlit/frontend/dist/assets/logo_dark-2a3cf740.svg
chainlit/frontend/dist/assets/logo_light-b078e7bc.svg
chainlit/frontend/dist/assets/react-plotly-f0315f86.js
chainlit/frontend/dist/favicon.svg
praisonai_ui-1.3.0rc8.dist-info/METADATA
praisonai_ui-1.3.0rc8.dist-info/WHEEL
praisonai_ui-1.3.0rc8.dist-info/entry_points.txt
praisonai_ui-1.3.0rc8.dist-info/RECORD
