Metadata-Version: 2.4
Name: praisonai-ui
Version: 1.3.0rc8
Summary: Modern AI Agent Chat Interface for PraisonAI
License: Apache-2.0 license
Keywords: LLM,Agents,gen ai,chat ui,chatbot ui,openai,copilot,langchain,conversational ai,praisonai,multi-agent
Author: praison
Requires-Python: >=3.9,<4.0.0
Classifier: License :: Other/Proprietary License
Classifier: Programming Language :: Python :: 3
Classifier: Programming Language :: Python :: 3.9
Classifier: Programming Language :: Python :: 3.10
Classifier: Programming Language :: Python :: 3.11
Classifier: Programming Language :: Python :: 3.12
Classifier: Programming Language :: Python :: 3.13
Classifier: Programming Language :: Python :: 3.14
Requires-Dist: aiofiles (>=23.1.0,<24.0.0)
Requires-Dist: asyncer (>=0.0.7,<0.0.8)
Requires-Dist: click (>=8.1.3,<9.0.0)
Requires-Dist: dataclasses_json (>=0.6.7,<0.7.0)
Requires-Dist: fastapi (>=0.110.1,<0.113)
Requires-Dist: filetype (>=1.2.0,<2.0.0)
Requires-Dist: httpx (>=0.23.0)
Requires-Dist: lazify (>=0.4.0,<0.5.0)
Requires-Dist: literalai (==0.0.623)
Requires-Dist: nest-asyncio (>=1.6.0,<2.0.0)
Requires-Dist: numpy (>=1.26,<2.0)
Requires-Dist: packaging (>=23.1,<24.0)
Requires-Dist: pydantic (>=1,<3)
Requires-Dist: pyjwt (>=2.8.0,<3.0.0)
Requires-Dist: python-dotenv (>=1.0.0,<2.0.0)
Requires-Dist: python-multipart (>=0.0.9,<0.0.10)
Requires-Dist: python-socketio (>=5.11.0,<6.0.0)
Requires-Dist: starlette (>=0.37.2,<0.38.0)
Requires-Dist: syncer (>=2.0.3,<3.0.0)
Requires-Dist: tomli (>=2.0.1,<3.0.0)
Requires-Dist: uptrace (>=1.22.0,<2.0.0)
Requires-Dist: uvicorn (>=0.25.0,<0.26.0)
Requires-Dist: watchfiles (>=0.20.0,<0.21.0)
Project-URL: Repository, https://github.com/MervinPraison/PraisonAI-UI
